Metadata-Version: 1.0
Name: aind-distributions
Version: 0.1.1
Summary: Gaussian and Binomial distributions
Home-page: UNKNOWN
Author: Will Olson
Author-email: will.olson11@gmail.com
License: UNKNOWN
Platform: UNKNOWN
